LICENSE
README.md
setup.py
pypi_scraper/__init__.py
so_scraper.egg-info/PKG-INFO
so_scraper.egg-info/SOURCES.txt
so_scraper.egg-info/dependency_links.txt
so_scraper.egg-info/requires.txt
so_scraper.egg-info/top_level.txt